{
  "General": {
    "Symbol": "MLS",
    "Name": "CPROP",
    "Description": "<p>CPROP’s<span> </span>mission is to drive standardization,<span> </span>automation<span> </span>and validation in real estate to enhance operational efficiencies, reduce costs, improve accuracy and reduce risks for all stakeholders using blockchain technology.</p><p>The CPROP platform will be accessed via<span> </span>web<span> </span>or mobile app providing a way for all users to find and interact/transact with one another.</p><p>All CPROP platform-related fees will be payable with a native token, the MLS. These MLS tokens will be used to pay for the various services provided by the platform such as fees for generating standardized documentation packages based on a smart contract algorithm, escrow services, government filings, and payment processing including cryptocurrency/fiat currency conversions.</p>",
    "Features": null,
    "Technology": null,
    "TotalCoinSupply": "100000000",
    "Algorithm": null,
    "ProofType": null,
    "BlockReward": null,
    "Explorer": null,
    "StartDate": "22/10/2017",
    "TotalCoinsMined": null,
    "Twitter": "@cryptoproperty",
    "Telegram": null,
    "Youtube": null,
    "Video": null,
    "BlockchainInfo": null,
    "Facebook": null,
    "Slack": null,
    "Website": null,
    "GitHub": null,
    "OnMarkets": [
      "BitTrex",
      "CCEX"
    ],
    "Wallets": {
      "desktop": {
        "win": null,
        "linux": null,
        "mac": null
      },
      "mobile": {
        "android": null,
        "ios": null
      },
      "types": []
    }
  },
  "ICO": {
    "Status": "Upcoming",
    "Description": "<p>CPROP’s<span> </span>mission is to drive standardization,<span> </span>automation<span> </span>and validation in real estate to enhance operational efficiencies, reduce costs, improve accuracy and reduce risks for all stakeholders using blockchain technology.</p><p>The CPROP platform will be accessed via<span> </span>web<span> </span>or mobile app<span> </span>providing<span> </span>a way for all users to find and interact/transact with one another.</p><p>All CPROP platform-related fees will be payable with a native token, the MLS. These MLS tokens will be used to pay for the various services provided by the platform such as fees for generating standardized documentation packages based on a smart contract algorithm, escrow services, government filings, and payment processing including cryptocurrency/fiat currency conversions.</p><p><strong>Team</strong>:</p><ul><li><strong>Adam Koehler;</strong> <a href=\"https://www.linkedin.com/in/adamkoehler/\" target=\"_blank\"><img style=\"width: 14px; height: 13px;\" src=\"/media/1383931/likedin_logo_final.png?width=14&amp;height=13\" alt=\"\" data-id=\"202867\"></a></li><li><strong>Sanford Selman;</strong><span> </span><a href=\"https://www.linkedin.com/in/sandyselman/\" target=\"_blank\"><img style=\"width: 14px; height: 13px;\" src=\"/media/1383931/likedin_logo_final.png?width=14&amp;height=13\" alt=\"\" data-id=\"202867\"></a></li><li><strong>Fabiano Távora;</strong><span> </span><a href=\"https://www.linkedin.com/in/fabiano-t%C3%A1vora-92a76423/\" target=\"_blank\"><img style=\"width: 14px; height: 13px;\" src=\"/media/1383931/likedin_logo_final.png?width=14&amp;height=13\" alt=\"\" data-id=\"202867\"></a></li><li><strong>Jay Fortin;</strong><span> </span><a href=\"https://www.linkedin.com/in/rjayfortin/\" target=\"_blank\"><img style=\"width: 14px; height: 13px;\" src=\"/media/1383931/likedin_logo_final.png?width=14&amp;height=13\" alt=\"\" data-id=\"202867\"></a></li><li><strong>Eric Wang;</strong><span> </span><a href=\"https://www.linkedin.com/in/eric-wang-44a01549/\" target=\"_blank\"><img style=\"width: 14px; height: 13px;\" src=\"/media/1383931/likedin_logo_final.png?width=14&amp;height=13\" alt=\"\" data-id=\"202867\"></a></li><li><strong>Saleh Bawazir;</strong><span> </span><a href=\"https://www.linkedin.com/in/saleh-bawazir-26805613/\" target=\"_blank\"><img style=\"width: 14px; height: 13px;\" src=\"/media/1383931/likedin_logo_final.png?width=14&amp;height=13\" alt=\"\" data-id=\"202867\"></a></li><li><strong>Luke Sestito;</strong><span> </span><a href=\"https://www.linkedin.com/in/luke-sestito-33867711/\" target=\"_blank\"><img style=\"width: 14px; height: 13px;\" src=\"/media/1383931/likedin_logo_final.png?width=14&amp;height=13\" alt=\"\" data-id=\"202867\"></a></li><li><strong>Justin Davis;</strong><span> </span><a href=\"https://www.linkedin.com/in/justin-davis-a057657/\" target=\"_blank\"><img style=\"width: 14px; height: 13px;\" src=\"/media/1383931/likedin_logo_final.png?width=14&amp;height=13\" alt=\"\" data-id=\"202867\"></a></li><li><strong>Steve Weathers;</strong><span> </span><a href=\"https://www.linkedin.com/in/steve-weathers-75a6b91/\" target=\"_blank\"><img style=\"width: 14px; height: 13px;\" src=\"/media/1383931/likedin_logo_final.png?width=14&amp;height=13\" alt=\"\" data-id=\"202867\"></a></li><li><strong>Jon Zinman;</strong><span> </span><a href=\"https://www.linkedin.com/in/jon-d-zinman-98aa969/\" target=\"_blank\"><img style=\"width: 14px; height: 13px;\" src=\"/media/1383931/likedin_logo_final.png?width=14&amp;height=13\" alt=\"\" data-id=\"202867\"></a></li><li><strong>Nick Selman;</strong><span> </span><a href=\"https://www.linkedin.com/in/nickselman\" target=\"_blank\"><img style=\"width: 14px; height: 13px;\" src=\"/media/1383931/likedin_logo_final.png?width=14&amp;height=13\" alt=\"\" data-id=\"202867\"></a></li><li><strong>Jeremy Begley;</strong><span> </span><a href=\"https://www.linkedin.com/in/jdbegley/\" target=\"_blank\"><img style=\"width: 14px; height: 13px;\" src=\"/media/1383931/likedin_logo_final.png?width=14&amp;height=13\" alt=\"\" data-id=\"202867\"></a></li><li><strong>James Spence;</strong></li></ul><p>CPROP&#39;s ICO token supply represents 50% of the total token supply (30% will be sold in Pre-ICO) so there will be a total of <span>50000000 </span>tokens available, for $0.50 each at the offering. The ICO funding target is $25,000,000 USD, the funding cap is $35,000,000 USD.</p><p><strong>Token Reserve Split:</strong></p><p><strong><img style=\"width: 475px; height: 233px;\" src=\"/media/9350698/ico_token.png?width=475&amp;height=233\" alt=\"\" data-id=\"234731\"></strong></p><p><strong>Application of Contributions:</strong></p><p><img style=\"width: 476px; height: 226px;\" src=\"/media/9350697/ico_dist.png?width=476&amp;height=226\" alt=\"\" data-id=\"234730\"></p>",
    "TokenType": "N/A",
    "WebsiteLink": "https://cprop.io/#contribute",
    "FundingCap": "35,000,000 USD",
    "FundingTarget": "25,000,000 USD",
    "Date": null,
    "EndDate": null,
    "FundsRaisedList": "N/A",
    "FundsRaisedUSD": "N/A",
    "StartPrice": "0.50",
    "StartPriceCurrency": "USD",
    "Jurisdiction": "N/A",
    "BlogLink": null,
    "WhitePaperLink": "https://cprop.io/wp-content/uploads/2017/08/CPROP-whitepaper-V1.8.pdf"
  },
  "ccId": "234707"
}